automata_mcp/__init__.py
automata_mcp/server.py
automata_mcp/state/state.py
automata_mcp/tools/check_page_contains_text.py
automata_mcp/tools/click_element.py
automata_mcp/tools/double_click.py
automata_mcp/tools/extract_text_from_page.py
automata_mcp/tools/finish.py
automata_mcp/tools/get_actionable_elemtns.py
automata_mcp/tools/get_element_attribute.py
automata_mcp/tools/get_element_text.py
automata_mcp/tools/get_page_url.py
automata_mcp/tools/go_back.py
automata_mcp/tools/go_forward.py
automata_mcp/tools/hover_element.py
automata_mcp/tools/navigate_to.py
automata_mcp/tools/open_browser.py
automata_mcp/tools/refresh_page.py
automata_mcp/tools/right_click_element.py
automata_mcp/tools/scroll_page.py
automata_mcp/tools/select_option.py
automata_mcp/tools/type_text.py
automata_mcp/utils/actionable_elements.py
automata_mcp/utils/install_playwright.py
automata_mcp/utils/reset_state.py
automata_mcp-0.2.1.dist-info/licenses/license
automata_mcp-0.2.1.dist-info/METADATA
automata_mcp-0.2.1.dist-info/WHEEL
automata_mcp-0.2.1.dist-info/entry_points.txt
automata_mcp-0.2.1.dist-info/top_level.txt
automata_mcp-0.2.1.dist-info/RECORD
