Metadata-Version: 2.4
Name: automata_mcp
Version: 0.2.1
Summary: MCP server for browser automation using Playwright
Author-email: Your Name <your.email@example.com>
License: MIT
Keywords: mcp,playwright,browser,automation,claude
Classifier: Development Status :: 3 - Alpha
Classifier: Intended Audience :: Developers
Classifier: License :: OSI Approved :: MIT License
Classifier: Programming Language :: Python :: 3
Classifier: Programming Language :: Python :: 3.10
Classifier: Programming Language :: Python :: 3.11
Classifier: Programming Language :: Python :: 3.12
Requires-Python: >=3.10
License-File: license
Requires-Dist: mcp>=0.9.0
Requires-Dist: playwright>=1.40.0
Provides-Extra: dev
Requires-Dist: pytest>=7.0.0; extra == "dev"
Requires-Dist: black>=23.0.0; extra == "dev"
Requires-Dist: ruff>=0.1.0; extra == "dev"
Dynamic: license-file
